kidraw/__init__.py
kidraw/icbuilder.py
kidraw/kidraw_test.py
kidraw/stdlib.py
kidraw/stdlib_test.py
kidraw/old/__init__.py
kidraw/old/devices.py
kidraw/old/symbols.py
kidraw-2.dist-info/DESCRIPTION.rst
kidraw-2.dist-info/METADATA
kidraw-2.dist-info/RECORD
kidraw-2.dist-info/WHEEL
kidraw-2.dist-info/metadata.json
kidraw-2.dist-info/top_level.txt
